custom_modal_admin/__init__.py
custom_modal_admin/admin.py
custom_modal_admin/apps.py
custom_modal_admin/static/css/jquery-ui.css
custom_modal_admin/static/js/custom_modal_admin.js
custom_modal_admin/static/js/jquery-ui.min.js
django_custom_modal_admin-1.0.0.dist-info/LICENSE.md
django_custom_modal_admin-1.0.0.dist-info/METADATA
django_custom_modal_admin-1.0.0.dist-info/WHEEL
django_custom_modal_admin-1.0.0.dist-info/top_level.txt
django_custom_modal_admin-1.0.0.dist-info/RECORD
