Metadata-Version: 2.1
Name: django-custom-modal-admin
Version: 1.0.0
Summary: Your project description goes here
Home-page: https://github.com/frankhood/django-custom-modal-admin
Author: FrankHood Business Solutions srl
Author-email: info@frankhood.it
License: MIT
Keywords: django-custom-modal-admin
Classifier: Development Status :: 3 - Alpha
Classifier: Framework :: Django :: 3.2
Classifier: Framework :: Django :: 4.2
Classifier: Intended Audience :: Developers
Classifier: License :: OSI Approved :: BSD License
Classifier: Natural Language :: English
Classifier: Programming Language :: Python :: 3.8
Classifier: Programming Language :: Python :: 3.9
Classifier: Programming Language :: Python :: 3.10
Classifier: Programming Language :: Python :: 3.11
License-File: LICENSE.md
Requires-Dist: Django >=3.2
